yeah_websocket_elay_py/__init__.py
yeah_websocket_elay_py/client.py
yeah_websocket_elay_py/server.py
yeah_websocket-0.0.2.dist-info/METADATA
yeah_websocket-0.0.2.dist-info/WHEEL
yeah_websocket-0.0.2.dist-info/top_level.txt
yeah_websocket-0.0.2.dist-info/RECORD
